LICENSE
MANIFEST.in
requirements.txt
setup.py
pycoinmon/__init__.py
pycoinmon/__main__.py
pycoinmon/ascii.py
pycoinmon/common.py
pycoinmon/core.py
pycoinmon/main.py
pycoinmon/metadata.py
pycoinmon.egg-info/PKG-INFO
pycoinmon.egg-info/SOURCES.txt
pycoinmon.egg-info/dependency_links.txt
pycoinmon.egg-info/entry_points.txt
pycoinmon.egg-info/requires.txt
pycoinmon.egg-info/top_level.txt