Metadata-Version: 1.1
Name: pycoinmon
Version: 0.4.7
Summary: The cryptocurrency price tool on CLI
Home-page: https://github.com/RDCH106/pycoinmon
Author: Rubén de Celis Hernández, Javier Barbadillo, Víctor Goñi
Author-email: contact@rdch106.hol.es
License: MIT
Download-URL: https://github.com/RDCH106/pycoinmon/archive/v0.4.7.tar.gz
Keywords: bitcoin criptocurrency crypto ticker python cli price-tracker command-line
Platform: UNKNOWN
Classifier: Programming Language :: Python
Classifier: Programming Language :: Python :: 2.7
Classifier: Programming Language :: Python :: 3.2
Classifier: Programming Language :: Python :: 3.3
Classifier: Programming Language :: Python :: 3.4
Classifier: Programming Language :: Python :: 3.5
Classifier: Programming Language :: Python :: 3.6
